dataset_manager/__init__.py
dataset_manager/dataset.py
dataset_manager/manager.py
dataset_manager/printer.py
tests/__init__.py
tests/test_dataset.py
tests/test_manager.py
tests/test_printer.py
tests/test_integration/__init__.py
tests/test_integration/test_dataset.py
tests/test_integration/test_server.py
dataset_manager-0.1.0.dist-info/LICENSE
dataset_manager-0.1.0.dist-info/METADATA
dataset_manager-0.1.0.dist-info/WHEEL
dataset_manager-0.1.0.dist-info/top_level.txt
dataset_manager-0.1.0.dist-info/RECORD
