Metadata-Version: 2.1
Name: dataset-manager
Version: 0.1.0
Summary: Manage and automatize datasets for data science projects.
Home-page: UNKNOWN
Author: Diogo Munaro Vieira
Author-email: diogo.mvieira@gmail.com
License: Apache 2
Platform: UNKNOWN
Requires-Dist: PyYAML (>=3.13)
Requires-Dist: fs (<2.5.0)
Requires-Dist: fs.archive (<0.7.0)
Requires-Dist: requests
Requires-Dist: PTable (==0.9.2)
